powerline_venvprompt/segments.py
powerline_venvprompt-1.0.1.dist-info/LICENSE.txt
powerline_venvprompt-1.0.1.dist-info/METADATA
powerline_venvprompt-1.0.1.dist-info/WHEEL
powerline_venvprompt-1.0.1.dist-info/top_level.txt
powerline_venvprompt-1.0.1.dist-info/RECORD
