Metadata-Version: 2.1
Name: powerline-venvprompt
Version: 1.0.1
Summary: A Powerline segment for showing the venv prompt.
Author-email: Steve Nicholson <ssteve@mac.com>
Project-URL: Homepage, https://github.com/ssteve/powerline-venvprompt
Project-URL: Issues, https://github.com/ssteve/powerline-venvprompt/issues
Classifier: Programming Language :: Python :: 3
Classifier: License :: OSI Approved :: MIT License
Classifier: Operating System :: OS Independent
Requires-Python: >=3.8
License-File: LICENSE.txt
